odoo/addons/iot_oca/README.rst
odoo/addons/iot_oca/__init__.py
odoo/addons/iot_oca/__manifest__.py
odoo/addons/iot_oca/i18n/es.po
odoo/addons/iot_oca/i18n/iot.pot
odoo/addons/iot_oca/i18n/iot_oca.pot
odoo/addons/iot_oca/migrations/13.0.1.0.0/post-migration.py
odoo/addons/iot_oca/models/__init__.py
odoo/addons/iot_oca/models/iot_device.py
odoo/addons/iot_oca/models/iot_device_action.py
odoo/addons/iot_oca/models/iot_device_group.py
odoo/addons/iot_oca/models/iot_device_tag.py
odoo/addons/iot_oca/models/iot_system.py
odoo/addons/iot_oca/models/iot_system_action.py
odoo/addons/iot_oca/readme/CONTRIBUTORS.rst
odoo/addons/iot_oca/readme/DESCRIPTION.rst
odoo/addons/iot_oca/security/iot_security.xml
odoo/addons/iot_oca/security/ir.model.access.csv
odoo/addons/iot_oca/static/description/icon.png
odoo/addons/iot_oca/static/description/icon.svg
odoo/addons/iot_oca/static/description/index.html
odoo/addons/iot_oca/tests/__init__.py
odoo/addons/iot_oca/tests/test_iot.py
odoo/addons/iot_oca/views/iot_device_group.xml
odoo/addons/iot_oca/views/iot_device_tag.xml
odoo/addons/iot_oca/views/iot_device_views.xml
odoo/addons/iot_oca/views/iot_menu.xml
odoo/addons/iot_oca/views/iot_system_views.xml
odoo13_addon_iot_oca-13.0.2.0.0.dist-info/METADATA
odoo13_addon_iot_oca-13.0.2.0.0.dist-info/WHEEL
odoo13_addon_iot_oca-13.0.2.0.0.dist-info/top_level.txt
odoo13_addon_iot_oca-13.0.2.0.0.dist-info/RECORD
